{
    "ایک": {
        "word": "ایک",
        "root": "",
        "meaning": "",
        "pos": "",
        "gender": "",
        "category": "",
        "register": "",
        "examples": [],
        "notes": "",
        "romanized": "",
        "frequency": 13
    },
    "میں": {
        "word": "میں",
        "root": "",
        "meaning": "",
        "pos": "",
        "gender": "",
        "category": "",
        "register": "",
        "examples": [],
        "notes": "",
        "romanized": "",
        "frequency": 12
    },
    "تھا": {
        "word": "تھا",
        "root": "",
        "meaning": "",
        "pos": "",
        "gender": "",
        "category": "",
        "register": "",
        "examples": [],
        "notes": "",
        "romanized": "",
        "frequency": 12
    },
    "کے": {
        "word": "کے",
        "root": "",
        "meaning": "",
        "pos": "",
        "gender": "",
        "category": "",
        "register": "",
        "examples": [],
        "notes": "",
        "romanized": "",
        "frequency": 12
    },
    "سے": {
        "word": "سے",
        "root": "",
        "meaning": "",
        "pos": "",
        "gender": "",
        "category": "",
        "register": "",
        "examples": [],
        "notes": "",
        "romanized": "",
        "frequency": 11
    },
    "اس": {
        "word": "اس",
        "root": "",
        "meaning": "",
        "pos": "",
        "gender": "",
        "category": "",
        "register": "",
        "examples": [],
        "notes": "",
        "romanized": "",
        "frequency": 11
    },
    "نے": {
        "word": "نے",
        "root": "",
        "meaning": "",
        "pos": "",
        "gender": "",
        "category": "",
        "register": "",
        "examples": [],
        "notes": "",
        "romanized": "",
        "frequency": 11
    },
    "اور": {
        "word": "اور",
        "root": "",
        "meaning": "",
        "pos": "",
        "gender": "",
        "category": "",
        "register": "",
        "examples": [],
        "notes": "",
        "romanized": "",
        "frequency": 10
    },
    "کا": {
        "word": "کا",
        "root": "",
        "meaning": "",
        "pos": "",
        "gender": "",
        "category": "",
        "register": "",
        "examples": [],
        "notes": "",
        "romanized": "",
        "frequency": 10
    },
    "علی": {
        "word": "علی",
        "root": "",
        "meaning": "",
        "pos": "",
        "gender": "",
        "category": "",
        "register": "",
        "examples": [],
        "notes": "",
        "romanized": "",
        "frequency": 9
    },
    "کی": {
        "word": "کی",
        "root": "",
        "meaning": "",
        "pos": "",
        "gender": "",
        "category": "",
        "register": "",
        "examples": [],
        "notes": "",
        "romanized": "",
        "frequency": 9
    },
    "جمیل": {
        "word": "جمیل",
        "root": "",
        "meaning": "",
        "pos": "",
        "gender": "",
        "category": "",
        "register": "",
        "examples": [],
        "notes": "",
        "romanized": "",
        "frequency": 8
    },
    "وہ": {
        "word": "وہ",
        "root": "",
        "meaning": "",
        "pos": "",
        "gender": "",
        "category": "",
        "register": "",
        "examples": [],
        "notes": "",
        "romanized": "",
        "frequency": 8
    },
    "سب": {
        "word": "سب",
        "root": "",
        "meaning": "",
        "pos": "",
        "gender": "",
        "category": "",
        "register": "",
        "examples": [],
        "notes": "",
        "romanized": "",
        "frequency": 7
    },
    "اسکول": {
        "word": "اسکول",
        "root": "",
        "meaning": "",
        "pos": "",
        "gender": "",
        "category": "",
        "register": "",
        "examples": [],
        "notes": "",
        "romanized": "",
        "frequency": 6
    },
    "دن": {
        "word": "دن",
        "root": "",
        "meaning": "",
        "pos": "",
        "gender": "",
        "category": "",
        "register": "",
        "examples": [],
        "notes": "",
        "romanized": "",
        "frequency": 6
    },
    "کو": {
        "word": "کو",
        "root": "",
        "meaning": "",
        "pos": "",
        "gender": "",
        "category": "",
        "register": "",
        "examples": [],
        "notes": "",
        "romanized": "",
        "frequency": 5
    },
    "مضمون": {
        "word": "مضمون",
        "root": "",
        "meaning": "",
        "pos": "",
        "gender": "",
        "category": "",
        "register": "",
        "examples": [],
        "notes": "",
        "romanized": "",
        "frequency": 4
    },
    "میری": {
        "word": "میری",
        "root": "",
        "meaning": "",
        "pos": "",
        "gender": "",
        "category": "",
        "register": "",
        "examples": [],
        "notes": "",
        "romanized": "",
        "frequency": 4
    },
    "زندگی": {
        "word": "زندگی",
        "root": "",
        "meaning": "",
        "pos": "",
        "gender": "",
        "category": "",
        "register": "",
        "examples": [],
        "notes": "",
        "romanized": "",
        "frequency": 3
    },
    "تھے": {
        "word": "تھے",
        "root": "",
        "meaning": "",
        "pos": "",
        "gender": "",
        "category": "",
        "register": "",
        "examples": [],
        "notes": "",
        "romanized": "",
        "frequency": 3
    },
    "اسے": {
        "word": "اسے",
        "root": "",
        "meaning": "",
        "pos": "",
        "gender": "",
        "category": "",
        "register": "",
        "examples": [],
        "notes": "",
        "romanized": "",
        "frequency": 3
    },
    "ہوا": {
        "word": "ہوا",
        "root": "",
        "meaning": "",
        "pos": "",
        "gender": "",
        "category": "",
        "register": "",
        "examples": [],
        "notes": "",
        "romanized": "",
        "frequency": 3
    },
    "اہم": {
        "word": "اہم",
        "root": "",
        "meaning": "",
        "pos": "",
        "gender": "",
        "category": "",
        "register": "",
        "examples": [],
        "notes": "",
        "romanized": "",
        "frequency": 3
    },
    "اپنے": {
        "word": "اپنے",
        "root": "",
        "meaning": "",
        "pos": "",
        "gender": "",
        "category": "",
        "register": "",
        "examples": [],
        "notes": "",
        "romanized": "",
        "frequency": 3
    },
    "بھی": {
        "word": "بھی",
        "root": "",
        "meaning": "",
        "pos": "",
        "gender": "",
        "category": "",
        "register": "",
        "examples": [],
        "notes": "",
        "romanized": "",
        "frequency": 3
    },
    "جب": {
        "word": "جب",
        "root": "",
        "meaning": "",
        "pos": "",
        "gender": "",
        "category": "",
        "register": "",
        "examples": [],
        "notes": "",
        "romanized": "",
        "frequency": 3
    },
    "کہ": {
        "word": "کہ",
        "root": "",
        "meaning": "",
        "pos": "",
        "gender": "",
        "category": "",
        "register": "",
        "examples": [],
        "notes": "",
        "romanized": "",
        "frequency": 3
    },
    "ہم": {
        "word": "ہم",
        "root": "",
        "meaning": "",
        "pos": "",
        "gender": "",
        "category": "",
        "register": "",
        "examples": [],
        "notes": "",
        "romanized": "",
        "frequency": 3
    },
    "گیا": {
        "word": "گیا",
        "root": "",
        "meaning": "",
        "pos": "",
        "gender": "",
        "category": "",
        "register": "",
        "examples": [],
        "notes": "",
        "romanized": "",
        "frequency": 3
    },
    "لیے": {
        "word": "لیے",
        "root": "",
        "meaning": "",
        "pos": "",
        "gender": "",
        "category": "",
        "register": "",
        "examples": [],
        "notes": "",
        "romanized": "",
        "frequency": 3
    },
    "تھی": {
        "word": "تھی",
        "root": "",
        "meaning": "",
        "pos": "",
        "gender": "",
        "category": "",
        "register": "",
        "examples": [],
        "notes": "",
        "romanized": "",
        "frequency": 2
    },
    "لڑکا": {
        "word": "لڑکا",
        "root": "",
        "meaning": "",
        "pos": "",
        "gender": "",
        "category": "",
        "register": "",
        "examples": [],
        "notes": "",
        "romanized": "",
        "frequency": 2
    },
    "جس": {
        "word": "جس",
        "root": "",
        "meaning": "",
        "pos": "",
        "gender": "",
        "category": "",
        "register": "",
        "examples": [],
        "notes": "",
        "romanized": "",
        "frequency": 2
    },
    "والد": {
        "word": "والد",
        "root": "",
        "meaning": "",
        "pos": "",
        "gender": "",
        "category": "",
        "register": "",
        "examples": [],
        "notes": "",
        "romanized": "",
        "frequency": 2
    },
    "ہر": {
        "word": "ہر",
        "root": "",
        "meaning": "",
        "pos": "",
        "gender": "",
        "category": "",
        "register": "",
        "examples": [],
        "notes": "",
        "romanized": "",
        "frequency": 2
    },
    "لیکن": {
        "word": "لیکن",
        "root": "",
        "meaning": "",
        "pos": "",
        "gender": "",
        "category": "",
        "register": "",
        "examples": [],
        "notes": "",
        "romanized": "",
        "frequency": 2
    },
    "دوسروں": {
        "word": "دوسروں",
        "root": "",
        "meaning": "",
        "pos": "",
        "gender": "",
        "category": "",
        "register": "",
        "examples": [],
        "notes": "",
        "romanized": "",
        "frequency": 2
    },
    "پر": {
        "word": "پر",
        "root": "",
        "meaning": "",
        "pos": "",
        "gender": "",
        "category": "",
        "register": "",
        "examples": [],
        "notes": "",
        "romanized": "",
        "frequency": 2
    },
    "خاموش": {
        "word": "خاموش",
        "root": "",
        "meaning": "",
        "pos": "",
        "gender": "",
        "category": "",
        "register": "",
        "examples": [],
        "notes": "",
        "romanized": "",
        "frequency": 2
    },
    "صرف": {
        "word": "صرف",
        "root": "",
        "meaning": "",
        "pos": "",
        "gender": "",
        "category": "",
        "register": "",
        "examples": [],
        "notes": "",
        "romanized": "",
        "frequency": 2
    },
    "روٹی": {
        "word": "روٹی",
        "root": "",
        "meaning": "",
        "pos": "",
        "gender": "",
        "category": "",
        "register": "",
        "examples": [],
        "notes": "",
        "romanized": "",
        "frequency": 2
    },
    "فقیر": {
        "word": "فقیر",
        "root": "",
        "meaning": "",
        "pos": "",
        "gender": "",
        "category": "",
        "register": "",
        "examples": [],
        "notes": "",
        "romanized": "",
        "frequency": 2
    },
    "بچوں": {
        "word": "بچوں",
        "root": "",
        "meaning": "",
        "pos": "",
        "gender": "",
        "category": "",
        "register": "",
        "examples": [],
        "notes": "",
        "romanized": "",
        "frequency": 2
    },
    "لکھا": {
        "word": "لکھا",
        "root": "",
        "meaning": "",
        "pos": "",
        "gender": "",
        "category": "",
        "register": "",
        "examples": [],
        "notes": "",
        "romanized": "",
        "frequency": 2
    },
    "حصہ": {
        "word": "حصہ",
        "root": "",
        "meaning": "",
        "pos": "",
        "gender": "",
        "category": "",
        "register": "",
        "examples": [],
        "notes": "",
        "romanized": "",
        "frequency": 2
    },
    "ماں": {
        "word": "ماں",
        "root": "",
        "meaning": "",
        "pos": "",
        "gender": "",
        "category": "",
        "register": "",
        "examples": [],
        "notes": "",
        "romanized": "",
        "frequency": 2
    },
    "اب": {
        "word": "اب",
        "root": "",
        "meaning": "",
        "pos": "",
        "gender": "",
        "category": "",
        "register": "",
        "examples": [],
        "notes": "",
        "romanized": "",
        "frequency": 2
    },
    "میرے": {
        "word": "میرے",
        "root": "",
        "meaning": "",
        "pos": "",
        "gender": "",
        "category": "",
        "register": "",
        "examples": [],
        "notes": "",
        "romanized": "",
        "frequency": 2
    },
    "کسی": {
        "word": "کسی",
        "root": "",
        "meaning": "",
        "pos": "",
        "gender": "",
        "category": "",
        "register": "",
        "examples": [],
        "notes": "",
        "romanized": "",
        "frequency": 2
    },
    "بلکہ": {
        "word": "بلکہ",
        "root": "",
        "meaning": "",
        "pos": "",
        "gender": "",
        "category": "",
        "register": "",
        "examples": [],
        "notes": "",
        "romanized": "",
        "frequency": 2
    },
    "بار": {
        "word": "بار",
        "root": "",
        "meaning": "",
        "pos": "",
        "gender": "",
        "category": "",
        "register": "",
        "examples": [],
        "notes": "",
        "romanized": "",
        "frequency": 2
    },
    "انسان": {
        "word": "انسان",
        "root": "",
        "meaning": "",
        "pos": "",
        "gender": "",
        "category": "",
        "register": "",
        "examples": [],
        "notes": "",
        "romanized": "",
        "frequency": 2
    },
    "آہستہ": {
        "word": "آہستہ",
        "root": "",
        "meaning": "",
        "pos": "",
        "gender": "",
        "category": "",
        "register": "",
        "examples": [],
        "notes": "",
        "romanized": "",
        "frequency": 2
    },
    "سوچ": {
        "word": "سوچ",
        "root": "",
        "meaning": "",
        "pos": "",
        "gender": "",
        "category": "",
        "register": "",
        "examples": [],
        "notes": "",
        "romanized": "",
        "frequency": 2
    },
    "لگا": {
        "word": "لگا",
        "root": "",
        "meaning": "",
        "pos": "",
        "gender": "",
        "category": "",
        "register": "",
        "examples": [],
        "notes": "",
        "romanized": "",
        "frequency": 2
    },
    "ہے": {
        "word": "ہے",
        "root": "",
        "meaning": "",
        "pos": "",
        "gender": "",
        "category": "",
        "register": "",
        "examples": [],
        "notes": "",
        "romanized": "",
        "frequency": 2
    },
    "چھوٹے": {
        "word": "چھوٹے",
        "root": "",
        "meaning": "",
        "pos": "",
        "gender": "",
        "category": "",
        "register": "",
        "examples": [],
        "notes": "",
        "romanized": "",
        "frequency": 1
    },
    "قصبے": {
        "word": "قصبے",
        "root": "",
        "meaning": "",
        "pos": "",
        "gender": "",
        "category": "",
        "register": "",
        "examples": [],
        "notes": "",
        "romanized": "",
        "frequency": 1
    },
    "جہاں": {
        "word": "جہاں",
        "root": "",
        "meaning": "",
        "pos": "",
        "gender": "",
        "category": "",
        "register": "",
        "examples": [],
        "notes": "",
        "romanized": "",
        "frequency": 1
    },
    "سادہ": {
        "word": "سادہ",
        "root": "",
        "meaning": "",
        "pos": "",
        "gender": "",
        "category": "",
        "register": "",
        "examples": [],
        "notes": "",
        "romanized": "",
        "frequency": 1
    },
    "لوگ": {
        "word": "لوگ",
        "root": "",
        "meaning": "",
        "pos": "",
        "gender": "",
        "category": "",
        "register": "",
        "examples": [],
        "notes": "",
        "romanized": "",
        "frequency": 1
    },
    "دوسرے": {
        "word": "دوسرے",
        "root": "",
        "meaning": "",
        "pos": "",
        "gender": "",
        "category": "",
        "register": "",
        "examples": [],
        "notes": "",
        "romanized": "",
        "frequency": 1
    },
    "جانتے": {
        "word": "جانتے",
        "root": "",
        "meaning": "",
        "pos": "",
        "gender": "",
        "category": "",
        "register": "",
        "examples": [],
        "notes": "",
        "romanized": "",
        "frequency": 1
    },
    "وہاں": {
        "word": "وہاں",
        "root": "",
        "meaning": "",
        "pos": "",
        "gender": "",
        "category": "",
        "register": "",
        "examples": [],
        "notes": "",
        "romanized": "",
        "frequency": 1
    },
    "رہتا": {
        "word": "رہتا",
        "root": "",
        "meaning": "",
        "pos": "",
        "gender": "",
        "category": "",
        "register": "",
        "examples": [],
        "notes": "",
        "romanized": "",
        "frequency": 1
    },
    "نام": {
        "word": "نام",
        "root": "",
        "meaning": "",
        "pos": "",
        "gender": "",
        "category": "",
        "register": "",
        "examples": [],
        "notes": "",
        "romanized": "",
        "frequency": 1
    },
    "امیر": {
        "word": "امیر",
        "root": "",
        "meaning": "",
        "pos": "",
        "gender": "",
        "category": "",
        "register": "",
        "examples": [],
        "notes": "",
        "romanized": "",
        "frequency": 1
    },
    "گھرانے": {
        "word": "گھرانے",
        "root": "",
        "meaning": "",
        "pos": "",
        "gender": "",
        "category": "",
        "register": "",
        "examples": [],
        "notes": "",
        "romanized": "",
        "frequency": 1
    },
    "تعلق": {
        "word": "تعلق",
        "root": "",
        "meaning": "",
        "pos": "",
        "gender": "",
        "category": "",
        "register": "",
        "examples": [],
        "notes": "",
        "romanized": "",
        "frequency": 1
    },
    "رکھتا": {
        "word": "رکھتا",
        "root": "",
        "meaning": "",
        "pos": "",
        "gender": "",
        "category": "",
        "register": "",
        "examples": [],
        "notes": "",
        "romanized": "",
        "frequency": 1
    },
    "شہر": {
        "word": "شہر",
        "root": "",
        "meaning": "",
        "pos": "",
        "gender": "",
        "category": "",
        "register": "",
        "examples": [],
        "notes": "",
        "romanized": "",
        "frequency": 1
    },
    "بڑے": {
        "word": "بڑے",
        "root": "",
        "meaning": "",
        "pos": "",
        "gender": "",
        "category": "",
        "register": "",
        "examples": [],
        "notes": "",
        "romanized": "",
        "frequency": 1
    },
    "تاجر": {
        "word": "تاجر",
        "root": "",
        "meaning": "",
        "pos": "",
        "gender": "",
        "category": "",
        "register": "",
        "examples": [],
        "notes": "",
        "romanized": "",
        "frequency": 1
    },
    "آسائش": {
        "word": "آسائش",
        "root": "",
        "meaning": "",
        "pos": "",
        "gender": "",
        "category": "",
        "register": "",
        "examples": [],
        "notes": "",
        "romanized": "",
        "frequency": 1
    },
    "میسر": {
        "word": "میسر",
        "root": "",
        "meaning": "",
        "pos": "",
        "gender": "",
        "category": "",
        "register": "",
        "examples": [],
        "notes": "",
        "romanized": "",
        "frequency": 1
    },
    "کمی": {
        "word": "کمی",
        "root": "",
        "meaning": "",
        "pos": "",
        "gender": "",
        "category": "",
        "register": "",
        "examples": [],
        "notes": "",
        "romanized": "",
        "frequency": 1
    },
    "تھیوہ": {
        "word": "تھیوہ",
        "root": "",
        "meaning": "",
        "pos": "",
        "gender": "",
        "category": "",
        "register": "",
        "examples": [],
        "notes": "",
        "romanized": "",
        "frequency": 1
    },
    "حقیر": {
        "word": "حقیر",
        "root": "",
        "meaning": "",
        "pos": "",
        "gender": "",
        "category": "",
        "register": "",
        "examples": [],
        "notes": "",
        "romanized": "",
        "frequency": 1
    },
    "سمجھتا": {
        "word": "سمجھتا",
        "root": "",
        "meaning": "",
        "pos": "",
        "gender": "",
        "category": "",
        "register": "",
        "examples": [],
        "notes": "",
        "romanized": "",
        "frequency": 1
    },
    "خاص": {
        "word": "خاص",
        "root": "",
        "meaning": "",
        "pos": "",
        "gender": "",
        "category": "",
        "register": "",
        "examples": [],
        "notes": "",
        "romanized": "",
        "frequency": 1
    },
    "طور": {
        "word": "طور",
        "root": "",
        "meaning": "",
        "pos": "",
        "gender": "",
        "category": "",
        "register": "",
        "examples": [],
        "notes": "",
        "romanized": "",
        "frequency": 1
    },
    "غریبوں": {
        "word": "غریبوں",
        "root": "",
        "meaning": "",
        "pos": "",
        "gender": "",
        "category": "",
        "register": "",
        "examples": [],
        "notes": "",
        "romanized": "",
        "frequency": 1
    },
    "جو": {
        "word": "جو",
        "root": "",
        "meaning": "",
        "pos": "",
        "gender": "",
        "category": "",
        "register": "",
        "examples": [],
        "notes": "",
        "romanized": "",
        "frequency": 1
    },
    "بہت": {
        "word": "بہت",
        "root": "",
        "meaning": "",
        "pos": "",
        "gender": "",
        "category": "",
        "register": "",
        "examples": [],
        "notes": "",
        "romanized": "",
        "frequency": 1
    },
    "طبیعت": {
        "word": "طبیعت",
        "root": "",
        "meaning": "",
        "pos": "",
        "gender": "",
        "category": "",
        "register": "",
        "examples": [],
        "notes": "",
        "romanized": "",
        "frequency": 1
    },
    "کپڑے": {
        "word": "کپڑے",
        "root": "",
        "meaning": "",
        "pos": "",
        "gender": "",
        "category": "",
        "register": "",
        "examples": [],
        "notes": "",
        "romanized": "",
        "frequency": 1
    },
    "پرانے": {
        "word": "پرانے",
        "root": "",
        "meaning": "",
        "pos": "",
        "gender": "",
        "category": "",
        "register": "",
        "examples": [],
        "notes": "",
        "romanized": "",
        "frequency": 1
    },
    "ہوتے": {
        "word": "ہوتے",
        "root": "",
        "meaning": "",
        "pos": "",
        "gender": "",
        "category": "",
        "register": "",
        "examples": [],
        "notes": "",
        "romanized": "",
        "frequency": 1
    },
    "جوتے": {
        "word": "جوتے",
        "root": "",
        "meaning": "",
        "pos": "",
        "gender": "",
        "category": "",
        "register": "",
        "examples": [],
        "notes": "",
        "romanized": "",
        "frequency": 1
    },
    "گھسے": {
        "word": "گھسے",
        "root": "",
        "meaning": "",
        "pos": "",
        "gender": "",
        "category": "",
        "register": "",
        "examples": [],
        "notes": "",
        "romanized": "",
        "frequency": 1
    },
    "ہوئے": {
        "word": "ہوئے",
        "root": "",
        "meaning": "",
        "pos": "",
        "gender": "",
        "category": "",
        "register": "",
        "examples": [],
        "notes": "",
        "romanized": "",
        "frequency": 1
    },
    "اکثر": {
        "word": "اکثر",
        "root": "",
        "meaning": "",
        "pos": "",
        "gender": "",
        "category": "",
        "register": "",
        "examples": [],
        "notes": "",
        "romanized": "",
        "frequency": 1
    },
    "دوپہر": {
        "word": "دوپہر",
        "root": "",
        "meaning": "",
        "pos": "",
        "gender": "",
        "category": "",
        "register": "",
        "examples": [],
        "notes": "",
        "romanized": "",
        "frequency": 1
    },
    "کھانے": {
        "word": "کھانے",
        "root": "",
        "meaning": "",
        "pos": "",
        "gender": "",
        "category": "",
        "register": "",
        "examples": [],
        "notes": "",
        "romanized": "",
        "frequency": 1
    },
    "کھاتا": {
        "word": "کھاتا",
        "root": "",
        "meaning": "",
        "pos": "",
        "gender": "",
        "category": "",
        "register": "",
        "examples": [],
        "notes": "",
        "romanized": "",
        "frequency": 1
    },
    "دوست": {
        "word": "دوست",
        "root": "",
        "meaning": "",
        "pos": "",
        "gender": "",
        "category": "",
        "register": "",
        "examples": [],
        "notes": "",
        "romanized": "",
        "frequency": 1
    },
    "مذاق": {
        "word": "مذاق",
        "root": "",
        "meaning": "",
        "pos": "",
        "gender": "",
        "category": "",
        "register": "",
        "examples": [],
        "notes": "",
        "romanized": "",
        "frequency": 1
    },
    "اُڑاتے": {
        "word": "اُڑاتے",
        "root": "",
        "meaning": "",
        "pos": "",
        "gender": "",
        "category": "",
        "register": "",
        "examples": [],
        "notes": "",
        "romanized": "",
        "frequency": 1
    },
    "کہتے": {
        "word": "کہتے",
        "root": "",
        "meaning": "",
        "pos": "",
        "gender": "",
        "category": "",
        "register": "",
        "examples": [],
        "notes": "",
        "romanized": "",
        "frequency": 1
    },
    "دور": {
        "word": "دور",
        "root": "",
        "meaning": "",
        "pos": "",
        "gender": "",
        "category": "",
        "register": "",
        "examples": [],
        "notes": "",
        "romanized": "",
        "frequency": 1
    },
    "رہتے": {
        "word": "رہتے",
        "root": "",
        "meaning": "",
        "pos": "",
        "gender": "",
        "category": "",
        "register": "",
        "examples": [],
        "notes": "",
        "romanized": "",
        "frequency": 1
    },
    "نویسی": {
        "word": "نویسی",
        "root": "",
        "meaning": "",
        "pos": "",
        "gender": "",
        "category": "",
        "register": "",
        "examples": [],
        "notes": "",
        "romanized": "",
        "frequency": 1
    },
    "مقابلہ": {
        "word": "مقابلہ",
        "root": "",
        "meaning": "",
        "pos": "",
        "gender": "",
        "category": "",
        "register": "",
        "examples": [],
        "notes": "",
        "romanized": "",
        "frequency": 1
    },
    "موضوع": {
        "word": "موضوع",
        "root": "",
        "meaning": "",
        "pos": "",
        "gender": "",
        "category": "",
        "register": "",
        "examples": [],
        "notes": "",
        "romanized": "",
        "frequency": 1
    },
    "تجربات": {
        "word": "تجربات",
        "root": "",
        "meaning": "",
        "pos": "",
        "gender": "",
        "category": "",
        "register": "",
        "examples": [],
        "notes": "",
        "romanized": "",
        "frequency": 1
    },
    "لکھے": {
        "word": "لکھے",
        "root": "",
        "meaning": "",
        "pos": "",
        "gender": "",
        "category": "",
        "register": "",
        "examples": [],
        "notes": "",
        "romanized": "",
        "frequency": 1
    },
    "یورپ": {
        "word": "یورپ",
        "root": "",
        "meaning": "",
        "pos": "",
        "gender": "",
        "category": "",
        "register": "",
        "examples": [],
        "notes": "",
        "romanized": "",
        "frequency": 1
    },
    "سفر": {
        "word": "سفر",
        "root": "",
        "meaning": "",
        "pos": "",
        "gender": "",
        "category": "",
        "register": "",
        "examples": [],
        "notes": "",
        "romanized": "",
        "frequency": 1
    },
    "ذکر": {
        "word": "ذکر",
        "root": "",
        "meaning": "",
        "pos": "",
        "gender": "",
        "category": "",
        "register": "",
        "examples": [],
        "notes": "",
        "romanized": "",
        "frequency": 1
    },
    "کیا": {
        "word": "کیا",
        "root": "",
        "meaning": "",
        "pos": "",
        "gender": "",
        "category": "",
        "register": "",
        "examples": [],
        "notes": "",
        "romanized": "",
        "frequency": 1
    },
    "مہنگے": {
        "word": "مہنگے",
        "root": "",
        "meaning": "",
        "pos": "",
        "gender": "",
        "category": "",
        "register": "",
        "examples": [],
        "notes": "",
        "romanized": "",
        "frequency": 1
    },
    "ہوٹل": {
        "word": "ہوٹل",
        "root": "",
        "meaning": "",
        "pos": "",
        "gender": "",
        "category": "",
        "register": "",
        "examples": [],
        "notes": "",
        "romanized": "",
        "frequency": 1
    },
    "شاپنگ": {
        "word": "شاپنگ",
        "root": "",
        "meaning": "",
        "pos": "",
        "gender": "",
        "category": "",
        "register": "",
        "examples": [],
        "notes": "",
        "romanized": "",
        "frequency": 1
    },
    "تفریح": {
        "word": "تفریح",
        "root": "",
        "meaning": "",
        "pos": "",
        "gender": "",
        "category": "",
        "register": "",
        "examples": [],
        "notes": "",
        "romanized": "",
        "frequency": 1
    },
    "لیا": {
        "word": "لیا",
        "root": "",
        "meaning": "",
        "pos": "",
        "gender": "",
        "category": "",
        "register": "",
        "examples": [],
        "notes": "",
        "romanized": "",
        "frequency": 1
    },
    "مختلف": {
        "word": "مختلف",
        "root": "",
        "meaning": "",
        "pos": "",
        "gender": "",
        "category": "",
        "register": "",
        "examples": [],
        "notes": "",
        "romanized": "",
        "frequency": 1
    },
    "مجھے": {
        "word": "مجھے",
        "root": "",
        "meaning": "",
        "pos": "",
        "gender": "",
        "category": "",
        "register": "",
        "examples": [],
        "notes": "",
        "romanized": "",
        "frequency": 1
    },
    "بتایا": {
        "word": "بتایا",
        "root": "",
        "meaning": "",
        "pos": "",
        "gender": "",
        "category": "",
        "register": "",
        "examples": [],
        "notes": "",
        "romanized": "",
        "frequency": 1
    },
    "زندہ": {
        "word": "زندہ",
        "root": "",
        "meaning": "",
        "pos": "",
        "gender": "",
        "category": "",
        "register": "",
        "examples": [],
        "notes": "",
        "romanized": "",
        "frequency": 1
    },
    "ہیں": {
        "word": "ہیں",
        "root": "",
        "meaning": "",
        "pos": "",
        "gender": "",
        "category": "",
        "register": "",
        "examples": [],
        "notes": "",
        "romanized": "",
        "frequency": 1
    },
    "حادثے": {
        "word": "حادثے",
        "root": "",
        "meaning": "",
        "pos": "",
        "gender": "",
        "category": "",
        "register": "",
        "examples": [],
        "notes": "",
        "romanized": "",
        "frequency": 1
    },
    "چل": {
        "word": "چل",
        "root": "",
        "meaning": "",
        "pos": "",
        "gender": "",
        "category": "",
        "register": "",
        "examples": [],
        "notes": "",
        "romanized": "",
        "frequency": 1
    },
    "بسے": {
        "word": "بسے",
        "root": "",
        "meaning": "",
        "pos": "",
        "gender": "",
        "category": "",
        "register": "",
        "examples": [],
        "notes": "",
        "romanized": "",
        "frequency": 1
    },
    "قرض": {
        "word": "قرض",
        "root": "",
        "meaning": "",
        "pos": "",
        "gender": "",
        "category": "",
        "register": "",
        "examples": [],
        "notes": "",
        "romanized": "",
        "frequency": 1
    },
    "چڑھ": {
        "word": "چڑھ",
        "root": "",
        "meaning": "",
        "pos": "",
        "gender": "",
        "category": "",
        "register": "",
        "examples": [],
        "notes": "",
        "romanized": "",
        "frequency": 1
    },
    "سلائی": {
        "word": "سلائی",
        "root": "",
        "meaning": "",
        "pos": "",
        "gender": "",
        "category": "",
        "register": "",
        "examples": [],
        "notes": "",
        "romanized": "",
        "frequency": 1
    },
    "شروع": {
        "word": "شروع",
        "root": "",
        "meaning": "",
        "pos": "",
        "gender": "",
        "category": "",
        "register": "",
        "examples": [],
        "notes": "",
        "romanized": "",
        "frequency": 1
    },
    "جانا": {
        "word": "جانا",
        "root": "",
        "meaning": "",
        "pos": "",
        "gender": "",
        "category": "",
        "register": "",
        "examples": [],
        "notes": "",
        "romanized": "",
        "frequency": 1
    },
    "جاری": {
        "word": "جاری",
        "root": "",
        "meaning": "",
        "pos": "",
        "gender": "",
        "category": "",
        "register": "",
        "examples": [],
        "notes": "",
        "romanized": "",
        "frequency": 1
    },
    "رکھا": {
        "word": "رکھا",
        "root": "",
        "meaning": "",
        "pos": "",
        "gender": "",
        "category": "",
        "register": "",
        "examples": [],
        "notes": "",
        "romanized": "",
        "frequency": 1
    },
    "دو": {
        "word": "دو",
        "root": "",
        "meaning": "",
        "pos": "",
        "gender": "",
        "category": "",
        "register": "",
        "examples": [],
        "notes": "",
        "romanized": "",
        "frequency": 1
    },
    "وقت": {
        "word": "وقت",
        "root": "",
        "meaning": "",
        "pos": "",
        "gender": "",
        "category": "",
        "register": "",
        "examples": [],
        "notes": "",
        "romanized": "",
        "frequency": 1
    },
    "کھائی": {
        "word": "کھائی",
        "root": "",
        "meaning": "",
        "pos": "",
        "gender": "",
        "category": "",
        "register": "",
        "examples": [],
        "notes": "",
        "romanized": "",
        "frequency": 1
    },
    "بغیر": {
        "word": "بغیر",
        "root": "",
        "meaning": "",
        "pos": "",
        "gender": "",
        "category": "",
        "register": "",
        "examples": [],
        "notes": "",
        "romanized": "",
        "frequency": 1
    },
    "ادھار": {
        "word": "ادھار",
        "root": "",
        "meaning": "",
        "pos": "",
        "gender": "",
        "category": "",
        "register": "",
        "examples": [],
        "notes": "",
        "romanized": "",
        "frequency": 1
    },
    "پورا": {
        "word": "پورا",
        "root": "",
        "meaning": "",
        "pos": "",
        "gender": "",
        "category": "",
        "register": "",
        "examples": [],
        "notes": "",
        "romanized": "",
        "frequency": 1
    },
    "ہو": {
        "word": "ہو",
        "root": "",
        "meaning": "",
        "pos": "",
        "gender": "",
        "category": "",
        "register": "",
        "examples": [],
        "notes": "",
        "romanized": "",
        "frequency": 1
    },
    "استاد": {
        "word": "استاد",
        "root": "",
        "meaning": "",
        "pos": "",
        "gender": "",
        "category": "",
        "register": "",
        "examples": [],
        "notes": "",
        "romanized": "",
        "frequency": 1
    },
    "آنکھوں": {
        "word": "آنکھوں",
        "root": "",
        "meaning": "",
        "pos": "",
        "gender": "",
        "category": "",
        "register": "",
        "examples": [],
        "notes": "",
        "romanized": "",
        "frequency": 1
    },
    "آنسو": {
        "word": "آنسو",
        "root": "",
        "meaning": "",
        "pos": "",
        "gender": "",
        "category": "",
        "register": "",
        "examples": [],
        "notes": "",
        "romanized": "",
        "frequency": 1
    },
    "نہ": {
        "word": "نہ",
        "root": "",
        "meaning": "",
        "pos": "",
        "gender": "",
        "category": "",
        "register": "",
        "examples": [],
        "notes": "",
        "romanized": "",
        "frequency": 1
    },
    "جیتا": {
        "word": "جیتا",
        "root": "",
        "meaning": "",
        "pos": "",
        "gender": "",
        "category": "",
        "register": "",
        "examples": [],
        "notes": "",
        "romanized": "",
        "frequency": 1
    },
    "دل": {
        "word": "دل",
        "root": "",
        "meaning": "",
        "pos": "",
        "gender": "",
        "category": "",
        "register": "",
        "examples": [],
        "notes": "",
        "romanized": "",
        "frequency": 1
    },
    "جیت": {
        "word": "جیت",
        "root": "",
        "meaning": "",
        "pos": "",
        "gender": "",
        "category": "",
        "register": "",
        "examples": [],
        "notes": "",
        "romanized": "",
        "frequency": 1
    },
    "پہلی": {
        "word": "پہلی",
        "root": "",
        "meaning": "",
        "pos": "",
        "gender": "",
        "category": "",
        "register": "",
        "examples": [],
        "notes": "",
        "romanized": "",
        "frequency": 1
    },
    "شرمندہ": {
        "word": "شرمندہ",
        "root": "",
        "meaning": "",
        "pos": "",
        "gender": "",
        "category": "",
        "register": "",
        "examples": [],
        "notes": "",
        "romanized": "",
        "frequency": 1
    },
    "احساس": {
        "word": "احساس",
        "root": "",
        "meaning": "",
        "pos": "",
        "gender": "",
        "category": "",
        "register": "",
        "examples": [],
        "notes": "",
        "romanized": "",
        "frequency": 1
    },
    "جسے": {
        "word": "جسے",
        "root": "",
        "meaning": "",
        "pos": "",
        "gender": "",
        "category": "",
        "register": "",
        "examples": [],
        "notes": "",
        "romanized": "",
        "frequency": 1
    },
    "کہتا": {
        "word": "کہتا",
        "root": "",
        "meaning": "",
        "pos": "",
        "gender": "",
        "category": "",
        "register": "",
        "examples": [],
        "notes": "",
        "romanized": "",
        "frequency": 1
    },
    "اصل": {
        "word": "اصل",
        "root": "",
        "meaning": "",
        "pos": "",
        "gender": "",
        "category": "",
        "register": "",
        "examples": [],
        "notes": "",
        "romanized": "",
        "frequency": 1
    },
    "بہادر": {
        "word": "بہادر",
        "root": "",
        "meaning": "",
        "pos": "",
        "gender": "",
        "category": "",
        "register": "",
        "examples": [],
        "notes": "",
        "romanized": "",
        "frequency": 1
    },
    "اگلے": {
        "word": "اگلے",
        "root": "",
        "meaning": "",
        "pos": "",
        "gender": "",
        "category": "",
        "register": "",
        "examples": [],
        "notes": "",
        "romanized": "",
        "frequency": 1
    },
    "معافی": {
        "word": "معافی",
        "root": "",
        "meaning": "",
        "pos": "",
        "gender": "",
        "category": "",
        "register": "",
        "examples": [],
        "notes": "",
        "romanized": "",
        "frequency": 1
    },
    "مانگی": {
        "word": "مانگی",
        "root": "",
        "meaning": "",
        "pos": "",
        "gender": "",
        "category": "",
        "register": "",
        "examples": [],
        "notes": "",
        "romanized": "",
        "frequency": 1
    },
    "ساتھ": {
        "word": "ساتھ",
        "root": "",
        "meaning": "",
        "pos": "",
        "gender": "",
        "category": "",
        "register": "",
        "examples": [],
        "notes": "",
        "romanized": "",
        "frequency": 1
    },
    "دوستی": {
        "word": "دوستی",
        "root": "",
        "meaning": "",
        "pos": "",
        "gender": "",
        "category": "",
        "register": "",
        "examples": [],
        "notes": "",
        "romanized": "",
        "frequency": 1
    },
    "بدلنے": {
        "word": "بدلنے",
        "root": "",
        "meaning": "",
        "pos": "",
        "gender": "",
        "category": "",
        "register": "",
        "examples": [],
        "notes": "",
        "romanized": "",
        "frequency": 1
    },
    "لگی": {
        "word": "لگی",
        "root": "",
        "meaning": "",
        "pos": "",
        "gender": "",
        "category": "",
        "register": "",
        "examples": [],
        "notes": "",
        "romanized": "",
        "frequency": 1
    },
    "مدد": {
        "word": "مدد",
        "root": "",
        "meaning": "",
        "pos": "",
        "gender": "",
        "category": "",
        "register": "",
        "examples": [],
        "notes": "",
        "romanized": "",
        "frequency": 1
    },
    "کرنے": {
        "word": "کرنے",
        "root": "",
        "meaning": "",
        "pos": "",
        "gender": "",
        "category": "",
        "register": "",
        "examples": [],
        "notes": "",
        "romanized": "",
        "frequency": 1
    },
    "فلاحی": {
        "word": "فلاحی",
        "root": "",
        "meaning": "",
        "pos": "",
        "gender": "",
        "category": "",
        "register": "",
        "examples": [],
        "notes": "",
        "romanized": "",
        "frequency": 1
    },
    "کاموں": {
        "word": "کاموں",
        "root": "",
        "meaning": "",
        "pos": "",
        "gender": "",
        "category": "",
        "register": "",
        "examples": [],
        "notes": "",
        "romanized": "",
        "frequency": 1
    },
    "لینے": {
        "word": "لینے",
        "root": "",
        "meaning": "",
        "pos": "",
        "gender": "",
        "category": "",
        "register": "",
        "examples": [],
        "notes": "",
        "romanized": "",
        "frequency": 1
    },
    "کئی": {
        "word": "کئی",
        "root": "",
        "meaning": "",
        "pos": "",
        "gender": "",
        "category": "",
        "register": "",
        "examples": [],
        "notes": "",
        "romanized": "",
        "frequency": 1
    },
    "سال": {
        "word": "سال",
        "root": "",
        "meaning": "",
        "pos": "",
        "gender": "",
        "category": "",
        "register": "",
        "examples": [],
        "notes": "",
        "romanized": "",
        "frequency": 1
    },
    "بعد": {
        "word": "بعد",
        "root": "",
        "meaning": "",
        "pos": "",
        "gender": "",
        "category": "",
        "register": "",
        "examples": [],
        "notes": "",
        "romanized": "",
        "frequency": 1
    },
    "سماجی": {
        "word": "سماجی",
        "root": "",
        "meaning": "",
        "pos": "",
        "gender": "",
        "category": "",
        "register": "",
        "examples": [],
        "notes": "",
        "romanized": "",
        "frequency": 1
    },
    "کارکن": {
        "word": "کارکن",
        "root": "",
        "meaning": "",
        "pos": "",
        "gender": "",
        "category": "",
        "register": "",
        "examples": [],
        "notes": "",
        "romanized": "",
        "frequency": 1
    },
    "بن": {
        "word": "بن",
        "root": "",
        "meaning": "",
        "pos": "",
        "gender": "",
        "category": "",
        "register": "",
        "examples": [],
        "notes": "",
        "romanized": "",
        "frequency": 1
    },
    "غریب": {
        "word": "غریب",
        "root": "",
        "meaning": "",
        "pos": "",
        "gender": "",
        "category": "",
        "register": "",
        "examples": [],
        "notes": "",
        "romanized": "",
        "frequency": 1
    },
    "بناتا": {
        "word": "بناتا",
        "root": "",
        "meaning": "",
        "pos": "",
        "gender": "",
        "category": "",
        "register": "",
        "examples": [],
        "notes": "",
        "romanized": "",
        "frequency": 1
    },
    "ان": {
        "word": "ان",
        "root": "",
        "meaning": "",
        "pos": "",
        "gender": "",
        "category": "",
        "register": "",
        "examples": [],
        "notes": "",
        "romanized": "",
        "frequency": 1
    },
    "تعلیم": {
        "word": "تعلیم",
        "root": "",
        "meaning": "",
        "pos": "",
        "gender": "",
        "category": "",
        "register": "",
        "examples": [],
        "notes": "",
        "romanized": "",
        "frequency": 1
    },
    "بندوبست": {
        "word": "بندوبست",
        "root": "",
        "meaning": "",
        "pos": "",
        "gender": "",
        "category": "",
        "register": "",
        "examples": [],
        "notes": "",
        "romanized": "",
        "frequency": 1
    },
    "کرتا": {
        "word": "کرتا",
        "root": "",
        "meaning": "",
        "pos": "",
        "gender": "",
        "category": "",
        "register": "",
        "examples": [],
        "notes": "",
        "romanized": "",
        "frequency": 1
    },
    "بچے": {
        "word": "بچے",
        "root": "",
        "meaning": "",
        "pos": "",
        "gender": "",
        "category": "",
        "register": "",
        "examples": [],
        "notes": "",
        "romanized": "",
        "frequency": 1
    },
    "پڑھتے": {
        "word": "پڑھتے",
        "root": "",
        "meaning": "",
        "pos": "",
        "gender": "",
        "category": "",
        "register": "",
        "examples": [],
        "notes": "",
        "romanized": "",
        "frequency": 1
    },
    "دیکھتا": {
        "word": "دیکھتا",
        "root": "",
        "meaning": "",
        "pos": "",
        "gender": "",
        "category": "",
        "register": "",
        "examples": [],
        "notes": "",
        "romanized": "",
        "frequency": 1
    },
    "یاد": {
        "word": "یاد",
        "root": "",
        "meaning": "",
        "pos": "",
        "gender": "",
        "category": "",
        "register": "",
        "examples": [],
        "notes": "",
        "romanized": "",
        "frequency": 1
    },
    "آتا": {
        "word": "آتا",
        "root": "",
        "meaning": "",
        "pos": "",
        "gender": "",
        "category": "",
        "register": "",
        "examples": [],
        "notes": "",
        "romanized": "",
        "frequency": 1
    },
    "یہ": {
        "word": "یہ",
        "root": "",
        "meaning": "",
        "pos": "",
        "gender": "",
        "category": "",
        "register": "",
        "examples": [],
        "notes": "",
        "romanized": "",
        "frequency": 1
    },
    "کہانی": {
        "word": "کہانی",
        "root": "",
        "meaning": "",
        "pos": "",
        "gender": "",
        "category": "",
        "register": "",
        "examples": [],
        "notes": "",
        "romanized": "",
        "frequency": 1
    },
    "ہمیں": {
        "word": "ہمیں",
        "root": "",
        "meaning": "",
        "pos": "",
        "gender": "",
        "category": "",
        "register": "",
        "examples": [],
        "notes": "",
        "romanized": "",
        "frequency": 1
    },
    "سکھاتی": {
        "word": "سکھاتی",
        "root": "",
        "meaning": "",
        "pos": "",
        "gender": "",
        "category": "",
        "register": "",
        "examples": [],
        "notes": "",
        "romanized": "",
        "frequency": 1
    },
    "عظمت": {
        "word": "عظمت",
        "root": "",
        "meaning": "",
        "pos": "",
        "gender": "",
        "category": "",
        "register": "",
        "examples": [],
        "notes": "",
        "romanized": "",
        "frequency": 1
    },
    "لباس": {
        "word": "لباس",
        "root": "",
        "meaning": "",
        "pos": "",
        "gender": "",
        "category": "",
        "register": "",
        "examples": [],
        "notes": "",
        "romanized": "",
        "frequency": 1
    },
    "یا": {
        "word": "یا",
        "root": "",
        "meaning": "",
        "pos": "",
        "gender": "",
        "category": "",
        "register": "",
        "examples": [],
        "notes": "",
        "romanized": "",
        "frequency": 1
    },
    "دولت": {
        "word": "دولت",
        "root": "",
        "meaning": "",
        "pos": "",
        "gender": "",
        "category": "",
        "register": "",
        "examples": [],
        "notes": "",
        "romanized": "",
        "frequency": 1
    },
    "نہیں": {
        "word": "نہیں",
        "root": "",
        "meaning": "",
        "pos": "",
        "gender": "",
        "category": "",
        "register": "",
        "examples": [],
        "notes": "",
        "romanized": "",
        "frequency": 1
    },
    "عمل": {
        "word": "عمل",
        "root": "",
        "meaning": "",
        "pos": "",
        "gender": "",
        "category": "",
        "register": "",
        "examples": [],
        "notes": "",
        "romanized": "",
        "frequency": 1
    },
    "ہوتی": {
        "word": "ہوتی",
        "root": "",
        "meaning": "",
        "pos": "",
        "gender": "",
        "category": "",
        "register": "",
        "examples": [],
        "notes": "",
        "romanized": "",
        "frequency": 1
    }
}